cyminiball/__init__.py
cyminiball/_compat.py
cyminiball/_wrap.cpython-310-darwin.so
cyminiball-2.1.1.dist-info/LICENSE
cyminiball-2.1.1.dist-info/METADATA
cyminiball-2.1.1.dist-info/WHEEL
cyminiball-2.1.1.dist-info/top_level.txt
cyminiball-2.1.1.dist-info/RECORD
