Metadata-Version: 2.1
Name: cyminiball
Version: 2.1.1
Summary: Compute the smallest bounding ball of a point cloud. Cython binding of the popular miniball utility. Fast!
Home-page: https://github.com/hirsch-lab/cyminiball
Author: Norman Juchler
License: LGPLv3
Keywords: miniball,geometry,fast
Platform: UNKNOWN
Classifier: Programming Language :: Python :: 3
Classifier: Programming Language :: Python :: 3.6
Classifier: Programming Language :: Python :: 3.7
Classifier: Programming Language :: Python :: 3.8
Classifier: Programming Language :: Python :: 3.9
Classifier: Programming Language :: Python :: Implementation :: CPython
Classifier: License :: OSI Approved :: GNU General Public License v3 (GPLv3)
Classifier: Operating System :: OS Independent
Classifier: Topic :: Scientific/Engineering :: Mathematics
Classifier: Topic :: Software Development :: Libraries
Classifier: Topic :: Utilities
Classifier: Intended Audience :: Developers
Classifier: Intended Audience :: Science/Research
Requires-Python: >=3.6
License-File: LICENSE
Requires-Dist: numpy (>=1.0)
Requires-Dist: importlib-metadata ; python_version < "3.8"
